clock_timer/__init__.py
clock_timer/clock_timer.py
clock_timer-0.1.6.dist-info/METADATA
clock_timer-0.1.6.dist-info/WHEEL
clock_timer-0.1.6.dist-info/top_level.txt
clock_timer-0.1.6.dist-info/RECORD
