Metadata-Version: 2.1
Name: clock-timer
Version: 0.1.6
Summary: clock_timer 是 Python 下的时间库，用于时间字符串处理，可在 Web 开发、数据分析 等领域使用。该库 80% 基于 datetime ，使用该库，您能更人性化地处理时间字符串，而无需每次查询 datetime 繁琐的接口。该库主要用于时间加减计算、获取时间对应的周数和星座、获取当前时间、获取时间戳、时间戳和时间字符串的转换 等功能。后期仍会不断优化，欢迎留言。
Home-page: UNKNOWN
Author: Cyberbolt
Author-email: 735245473@qq.com
License: UNKNOWN
Platform: UNKNOWN
Classifier: Programming Language :: Python :: 3
Classifier: License :: OSI Approved :: MIT License
Classifier: Operating System :: OS Independent
